{
  "response": [
    {
      "maintainer": "objecting_",
      "currently_maintained": true,
      "oem": "Samsung",
      "device": "Galaxy Tab S6 Lite",
      "filename": "EvolutionX-16.0-20260101-gta4xl-11.4.2-Official.zip",
      "download": "https://cdn.evolution-x.org/gta4xl/16/EvolutionX-16.0-20260101-gta4xl-11.4.2-Official.zip/download",
      "timestamp": 1767305262,
      "md5": "ae1387c35bca33941e35f63931fdc11b",
      "sha256": "53d0eb49b106e29875d07e9ec46d71091a158254aa7aeb8c3636fc3c06dcfe6e",
      "size": 2656467457,
      "version": "11.4.2",
      "buildtype": "userdebug",
      "forum": "https://xdaforums.com/t/official-rom-15-evolutionx-for-the-galaxy-tab-s6-lite-series.4743017/",
      "firmware": "",
      "paypal": "",
      "github": "techyguyperplexable",
      "initial_installation_images": [
        "recovery"
      ],
      "extra_images": []
    }
  ]
}
