{
  "response": [
    {
      "maintainer": "Provasish Nandi",
      "currently_maintained": true,
      "oem": "Realme",
      "device": "GT Neo 3T",
      "filename": "EvolutionX-16.0-20251216-spartan-11.4.2-Official.zip",
      "download": "https://cdn.evolution-x.org/spartan/16/EvolutionX-16.0-20251216-spartan-11.4.2-Official.zip/download",
      "timestamp": 1765871570,
      "md5": "1fba01e5b650717ad6462554ad8b6913",
      "sha256": "d8b227c24b56df251874fd42c3e14b4eacc40bebb2919f0610f01fa20663fda4",
      "size": 3205202754,
      "version": "11.4.2",
      "buildtype": "userdebug",
      "forum": "",
      "firmware": "https://sourceforge.net/projects/rmx3371-builds/files/Firmware/A14-FW.zip/download",
      "paypal": "",
      "github": "provasish",
      "initial_installation_images": [
        "boot",
        "dtbo",
        "recovery"
      ],
      "extra_images": []
    }
  ]
}
